Metadata-Version: 2.1
Name: lib-python-jd
Version: 0.1
Summary: Módulo para exemplificar construção de projetos Python no curso
Home-page: https://github.com/JuniorD-Isael/lib_python_jd
Author: Junior Dorneles
Author-email: isaeldjunior@gmail.com
License:                     GNU AFFERO GENERAL PUBLIC LICENSE
Classifier: Development Status :: 2 - Pre-Alpha
Classifier: Environment :: Console
Classifier: Intended Audience :: Developers
Classifier: License :: OSI Approved :: GNU Affero General Public License v3 or later (AGPLv3+)
Classifier: Operating System :: OS Independent
Classifier: Programming Language :: Python :: 3.10
Classifier: Framework :: Pytest
License-File: LICENSE
